deepgnn/__init__.py
deepgnn/arg_types.py
deepgnn/log_consts.py
deepgnn/logging_utils.py
deepgnn/train_types.py
deepgnn/graph_engine/__init__.py
deepgnn/graph_engine/_adl_reader.py
deepgnn/graph_engine/_base.py
deepgnn/graph_engine/adl_uploader.py
deepgnn/graph_engine/graph_dataset.py
deepgnn/graph_engine/graph_ops.py
deepgnn/graph_engine/multihop.py
deepgnn/graph_engine/prefetch.py
deepgnn/graph_engine/samplers.py
deepgnn/graph_engine/test_adl_reader.py
deepgnn/graph_engine/test_multihop.py
deepgnn/graph_engine/test_prefetch.py
deepgnn/graph_engine/utils.py
deepgnn/graph_engine/backends/__init__.py
deepgnn/graph_engine/backends/common.py
deepgnn/graph_engine/backends/options.py
deepgnn/graph_engine/backends/snark/__init__.py
deepgnn/graph_engine/backends/snark/client.py
deepgnn/graph_engine/backends/snark/synchronized.py
deepgnn/graph_engine/backends/snark/test_snark_client.py
deepgnn/graph_engine/backends/snark/test_synchronized.py
deepgnn/graph_engine/data/__init__.py
deepgnn/graph_engine/data/citation.py
deepgnn/graph_engine/data/citeseer.py
deepgnn/graph_engine/data/cora.py
deepgnn/graph_engine/data/data_util.py
deepgnn/graph_engine/data/mooc.py
deepgnn/graph_engine/data/ppi.py
deepgnn/graph_engine/data/reddit.py
deepgnn/graph_engine/data/test_graph_dataset.py
deepgnn/graph_engine/snark/__init__.py
deepgnn/graph_engine/snark/_downloader.py
deepgnn/graph_engine/snark/_lib.py
deepgnn/graph_engine/snark/alias.py
deepgnn/graph_engine/snark/client.py
deepgnn/graph_engine/snark/convert.py
deepgnn/graph_engine/snark/decoders.py
deepgnn/graph_engine/snark/dispatcher.py
deepgnn/graph_engine/snark/distributed.py
deepgnn/graph_engine/snark/local.py
deepgnn/graph_engine/snark/meta.py
deepgnn/graph_engine/snark/meta_merger.py
deepgnn/graph_engine/snark/server.py
deepgnn/graph_engine/snark/wrapper.dll
deepgnn/graph_engine/snark/converter/__init__.py
deepgnn/graph_engine/snark/converter/options.py
deepgnn/graph_engine/snark/converter/process.py
deepgnn_ge-0.1.66.dist-info/METADATA
deepgnn_ge-0.1.66.dist-info/WHEEL
deepgnn_ge-0.1.66.dist-info/top_level.txt
deepgnn_ge-0.1.66.dist-info/RECORD
