Metadata-Version: 2.1
Name: deepgnn-ge
Version: 0.1.66
Summary: Graph engine - distributed graph engine to host graphs.
Home-page: https://github.com/microsoft/DeepGNN
Author: DeepGNN Team
Author-email: DeepGNN@microsoft.com
License: MIT
Project-URL: Source, https://github.com/microsoft/DeepGNN
Classifier: Development Status :: 3 - Alpha
Classifier: Intended Audience :: Developers
Classifier: Intended Audience :: Science/Research
Classifier: License :: OSI Approved :: MIT License
Classifier: Programming Language :: C++
Classifier: Programming Language :: Python :: 3
Classifier: Programming Language :: Python :: 3.7
Classifier: Programming Language :: Python :: 3.8
Classifier: Programming Language :: Python :: 3.9
Classifier: Programming Language :: Python :: 3.10
Classifier: Topic :: Scientific/Engineering
Classifier: Topic :: Software Development :: Libraries
Requires-Python: >=3.7
Requires-Dist: numpy>=1.17.0
Requires-Dist: networkx==2.5.1
Requires-Dist: azure-datalake-store
Requires-Dist: opencensus-ext-azure
Requires-Dist: fsspec>=2021.8.1
Requires-Dist: scikit-learn
Requires-Dist: scipy>=1.10.0
Requires-Dist: tenacity>=8
